[
  {
  "nombreCancion": "Libertango",
  "nombreAutor": "Alberto Piazzolla",
  "linkVideo": "https://www.youtube.com/watch?v=kdhTodxH7Gw"
},
  {
    "nombreCancion": "El huracan",
    "nombreAutor": "Solo Tango Orquesta",
    "linkVideo": "https://www.youtube.com/watch?v=-7S0Rnvb24Y"
  },
  {
    "nombreCancion": "Libertango",
    "nombreAutor": "Alberto Piazzolla",
    "linkVideo": "https://www.youtube.com/watch?v=kdhTodxH7Gw"
  },
  {
    "nombreCancion": "El huracan",
    "nombreAutor": "Solo Tango Orquesta",
    "linkVideo": "https://www.youtube.com/watch?v=-7S0Rnvb24Y"
  },
  {
    "nombreCancion": "Libertango",
    "nombreAutor": "Alberto Piazzolla",
    "linkVideo": "https://www.youtube.com/watch?v=kdhTodxH7Gw"
  },
  {
    "nombreCancion": "El huracan",
    "nombreAutor": "Solo Tango Orquesta",
    "linkVideo": "https://www.youtube.com/watch?v=-7S0Rnvb24Y"
  },
  {
    "nombreCancion": "Libertango",
    "nombreAutor": "Alberto Piazzolla",
    "linkVideo": "https://www.youtube.com/watch?v=kdhTodxH7Gw"
  },
  {
    "nombreCancion": "El huracan",
    "nombreAutor": "Solo Tango Orquesta",
    "linkVideo": "https://www.youtube.com/watch?v=-7S0Rnvb24Y"
  }

]